talus_python-0.2.3.dist-info/METADATA
talus_python-0.2.3.dist-info/WHEEL
talus_python/__init__.py
talus_python/__pycache__/morse.cpython-37.pyc
talus_python/__pycache__/__init__.cpython-37.pyc
talus_python/morse.py
talus_python/talus_python.cpython-37m-darwin.so
talus_python-0.2.3.dist-info/RECORD
