Metadata-Version: 2.1
Name: talus_python
Version: 0.2.3
Requires-Dist: networkx>=2.0
Summary: Computational topology in Rust
Author: Scott Hellman <scotthellman2@gmail.com>
Author-Email: Scott Hellman <scotthellman2@gmail.com>
License: MIT
